wrepl/__init__.py
wrepl/watcher.py
wrepl-0.0.20.dist-info/METADATA
wrepl-0.0.20.dist-info/WHEEL
wrepl-0.0.20.dist-info/entry_points.txt
wrepl-0.0.20.dist-info/top_level.txt
wrepl-0.0.20.dist-info/RECORD
