Metadata-Version: 2.1
Name: wrepl
Version: 0.0.20
Summary: Watch-Read-Eval-Print Loop
Home-page: https://github.com/octaltree/wrepl
Author: octaltree
Author-email: octalreee@gmail.com
License: MIT
Keywords: wrepl
Platform: UNKNOWN
Classifier: Development Status :: 3 - Alpha
Requires-Dist: watchdog
Requires-Dist: dill
